llmt/__init__.py
llmt/assistants.py
llmt/consts.py
llmt/core.py
llmt/exceptions.py
llmt/json_type.py
llmt/managers.py
llmt/openai_types.py
llmt/prompts.py
llmt/response.txt.j2
llmt/utils.py
llmt-0.0.5.dist-info/LICENSE
llmt-0.0.5.dist-info/METADATA
llmt-0.0.5.dist-info/WHEEL
llmt-0.0.5.dist-info/top_level.txt
llmt-0.0.5.dist-info/RECORD
