Metadata-Version: 2.1
Name: llmt
Version: 0.0.5
Summary: LLMT aims to make it easy to programatically connect OpenAI and HuggingFace models to your data pipelines, CI/CD, or personal workspaces.
Author-email: Artem Golub <artem@outermeasure.com>
Project-URL: Homepage, https://github.com/omhq/llmt
Project-URL: Bug Tracker, https://github.com/omhq/llmt/issues
Classifier: Programming Language :: Python :: 3
Classifier: License :: OSI Approved :: MIT License
Classifier: Operating System :: OS Independent
Requires-Python: >=3.12
License-File: LICENSE
Requires-Dist: openai ==1.14.1
Requires-Dist: requests ==2.31.0
Requires-Dist: watchdog ==4.0.0
Requires-Dist: halo ==0.0.31
Requires-Dist: inquirer ==3.2.4
Requires-Dist: Jinja2 ==3.1.3
Requires-Dist: PyYAML ==6.0.1
Requires-Dist: docstring-parser ==0.16
Requires-Dist: typing-extensions ==4.10.0
Requires-Dist: numpy ==1.26.4
Requires-Dist: pandas ==2.2.1
Requires-Dist: psycopg2-binary ==2.9.9
Requires-Dist: SQLAlchemy ==2.0.28
Requires-Dist: pydantic ==2.6.4
